lightnovel/__init__.py
lightnovel/api.py
lightnovel/epub.py
lightnovel/pipeline.py
lightnovel/util/__init__.py
lightnovel/util/other.py
lightnovel/util/sink.py
lightnovel/util/text.py
lightnovel/webnovel_com/__init__.py
lightnovel/wuxiaworld_com/__init__.py
lightnovel/wuxiaworld_com/api.py
lightnovelapi-0.2.dist-info/LICENSE
lightnovelapi-0.2.dist-info/METADATA
lightnovelapi-0.2.dist-info/WHEEL
lightnovelapi-0.2.dist-info/top_level.txt
lightnovelapi-0.2.dist-info/RECORD
